<?xml version="1.0" encoding="UTF-8"?>
<process-definition name="MainProcess" xmlns="urn:jbpm.org:jpdl-3.2">
  <description><![CDATA[MainProcess for subprocess demonstration (no start form provided)]]></description>
  <swimlane name="a_role">
    <assignment
      class="ru.runa.wf.jbpm.delegation.assignment.AssignmentHandler" config-type="configuration-property"><![CDATA[]]></assignment>
  </swimlane>
  <start-state name="start">
    <task name="start" swimlane="a_role"/>
    <transition name="tr1" to="before subprocess"/>
  </start-state>
  <task-node name="before subprocess">
    <description><![CDATA[before subprocess]]></description>
    <task name="before subprocess" swimlane="a_role"/>
    <transition name="tr1" to="process-state"/>
  </task-node>
  <task-node name="after subprocess">
    <description><![CDATA[after subprocess]]></description>
    <task name="after subprocess" swimlane="a_role"/>
    <transition name="tr1" to="end"/>
  </task-node>
  <process-state name="process-state">
    <transition name="tr1" to="after subprocess"/>
    <sub-process binding="late" name="SubProcess"/>
    <variable access="read" mapped-name="role1" name="a_role"/>
    <variable access="read,write" mapped-name="n" name="число"/>
    <variable access="read,write" mapped-name="d" name="дата"/>
  </process-state>
  <event type="subprocess-created">
    <action
      class="ru.runa.wf.jbpm.delegation.action.SetSubProcessPermissionsActionHandler" config-type="configuration-property"><![CDATA[]]></action>
  </event>
  <end-state name="end"/>
</process-definition>
