<?xml version="1.0" encoding="UTF-8"?>
<process-diagram height="441" name="WebService - who is" notation="bpmn"
  showActions="false" showGrid="false" width="480">
  <node height="48" name="Start" width="48" x="72" y="48">
    <transition name="tr1"/>
  </node>
  <node height="96" minimizedView="false" name="Load whois information"
    width="132" x="24" y="120">
    <transition name="tr1"/>
  </node>
  <node height="96" minimizedView="false"
    name="Read DNS address information" width="132" x="24" y="216">
    <transition name="tr1"/>
  </node>
  <node height="48" name="End" width="48" x="72" y="324"/>
</process-diagram>
